chaoshoneycomb/__init__.py
chaoshoneycomb/__version__.py
chaoshoneycomb/marker/__init__.py
chaoshoneycomb/marker/actions.py
chaoshoneycomb/query/__init__.py
chaoshoneycomb/query/probes.py
chaoshoneycomb/slo/__init__.py
chaoshoneycomb/slo/probes.py
chaoshoneycomb/trigger/__init__.py
chaoshoneycomb/trigger/probes.py
chaostoolkit_honeycomb-0.6.2.dist-info/METADATA
chaostoolkit_honeycomb-0.6.2.dist-info/WHEEL
chaostoolkit_honeycomb-0.6.2.dist-info/licenses/LICENSE
chaostoolkit_honeycomb-0.6.2.dist-info/RECORD
