Metadata-Version: 2.1
Name: chaostoolkit-honeycomb
Version: 0.6.2
Summary: Chaos Toolkit extension for Honeycomb
Author-Email: Sylvain Hellegouarch <sh@defuze.org>
License: Apache-2.0
Classifier: Development Status :: 5 - Production/Stable
Classifier: Intended Audience :: Developers
Classifier: License :: Freely Distributable
Classifier: License :: OSI Approved :: Apache Software License
Classifier: Operating System :: OS Independent
Classifier: Programming Language :: Python
Classifier: Programming Language :: Python :: 3
Classifier: Programming Language :: Python :: 3.7
Classifier: Programming Language :: Python :: 3.8
Classifier: Programming Language :: Python :: 3.9
Classifier: Programming Language :: Python :: 3.10
Classifier: Programming Language :: Python :: 3.11
Classifier: Programming Language :: Python :: 3.12
Classifier: Programming Language :: Python :: Implementation
Classifier: Programming Language :: Python :: Implementation :: CPython
Project-URL: Documentation, https://chaostoolkit.org
Project-URL: Repository, https://github.com/chaostoolkit-incubator/chaostoolkit-honeycomb
Project-URL: Changelog, https://github.com/chaostoolkit-incubator/chaostoolkit-honeycomb/blob/master/CHANGELOG.md
Requires-Python: >=3.7
Requires-Dist: chaostoolkit-lib>=1.37
Requires-Dist: httpx[http2]>=0.24.1
